{"card_name": "Revolutionary Throng", "color": "R", "rarity": "common", "type": "Creature \u2013 Human Rogue", "number": 120, "color_identity": "R", "cost": "{2}{R}", "rules_text": "Trample\nWhenever Revolutionary Throng attacks, if you control another creature with power 4 or greater, it gets +2/+0 until end of turn.", "flavor_text": "[i]A regime is nothing more than a dressed-up line of dominoes. Once one institution falls, the fates of the rest are sealed.[/i]", "pt": "2/3", "special_text": "", "shape": "normal", "set": "CNY", "loyalty": "", "artist": "Thomas Elliott", "notes": "Art Validated", "image_type": "jpg"}