{"card_name": "Assault Engine", "color": "UBR", "rarity": "uncommon", "type": "Artifact \u2013 Vehicle", "number": 158, "color_identity": "UBR", "cost": "{3}{U}{B}{R}", "rules_text": "Haste\nWhen Assault Engine enters, gain control of target creature and untap it. Sacrifice it at the beginning of the next end step. [i](It's still affected by summoning sickness, but can crew.)[/i]\nCrew 2", "flavor_text": "[i][/i]", "pt": "5/5", "special_text": "", "shape": "normal", "set": "CNY", "loyalty": "", "artist": "Eldon Cowgur", "notes": "Art Validated", "image_type": "jpg"}