{"card_name": "Bioengineered Opus", "color": "WUG", "rarity": "uncommon", "type": "Creature \u2013 Octopus Horror", "number": 160, "color_identity": "WUG", "cost": "{1}{G}{W}{U}", "rules_text": "Bioengineered Opus enters with three +1/+1 counters, a lifelink counter, and a vigilance counter on it.\nWhen Bioengineered Opus dies, for each creature you control, you may move a counter from Bioengineered Opus onto that creature.", "pt": "0/0", "special_text": "", "shape": "normal", "set": "CNY", "loyalty": "", "notes": "Art Validated"}