{"card_name": "High Senator Talpa", "color": "WU", "rarity": "mythic", "type": "Legendary Creature \u2013 Human Advisor", "number": 191, "color_identity": "WU", "cost": "{2}{W}{U}", "rules_text": "When High Senator Talpa enters, choose target opponent. If you control fewer creatures than that player, create a number of 1/1 colorless Soldier creature tokens equal to the difference. If you have fewer cards in hand than that player, draw cards equal to the difference.", "pt": "3/3", "special_text": "", "shape": "normal", "set": "CNY", "loyalty": "", "notes": "Art Validated"}