{"card_name": "Mondo, Outcast Maverick", "color": "WRG", "rarity": "uncommon", "type": "Legendary Creature \u2013 Human Rogue", "number": 197, "color_identity": "WRG", "cost": "{2}{R}{G}{W}", "rules_text": "Trample\nWhenever Mondo attacks, create a 1/1 colorless Soldier creature token that's tapped and attacking, then Mondo gets +X/+0 until end of turn, where X is the number of attacking creatures.", "flavor_text": "[i][/i]", "pt": "3/4", "special_text": "", "shape": "normal", "set": "CNY", "loyalty": "", "artist": "Aboy Singh", "notes": "Art Validated", "image_type": "jpg"}