{"card_name": "Night Squad", "color": "B", "rarity": "common", "type": "Creature \u2013 Human Assassin", "number": 83, "color_identity": "B", "cost": "{3}{B}", "rules_text": "When Night Squad enters, teach target creature menace. If you put a +1/+1 counter on it this way, it can't be blocked this turn. [i](To teach menace, put a menace counter on it. If it already has menace, put a +1/+1 counter on it instead.)[/i]", "flavor_text": "[i][/i]", "pt": "4/2", "special_text": "", "shape": "normal", "set": "CNY", "loyalty": "", "artist": "Goran Bukvic", "notes": "Art Validated", "image_type": "jpg"}